flattener/__init__.py
flattener/core.py
solidity_flattener-0.2.2.data/scripts/solidity_flattener
solidity_flattener-0.2.2.dist-info/DESCRIPTION.rst
solidity_flattener-0.2.2.dist-info/METADATA
solidity_flattener-0.2.2.dist-info/RECORD
solidity_flattener-0.2.2.dist-info/WHEEL
solidity_flattener-0.2.2.dist-info/metadata.json
solidity_flattener-0.2.2.dist-info/top_level.txt
